{
  "project_info": {
    "project_number": "514391608735",
    "project_id": "insubria-survive-7979f",
    "storage_bucket": "insubria-survive-7979f.firebasestorage.app"
  },
  "client": [
    {
      "client_info": {
        "mobilesdk_app_id": "1:514391608735:android:10ca0bf382e3a00a2681aa",
        "android_client_info": {
          "package_name": "com.example.insubria_survive"
        }
      },
      "oauth_client": [
        {
          "client_id": "514391608735-6i5eu3ksikmu29hp3gpkuu2711lkdhd9.apps.googleusercontent.com",
          "client_type": 1,
          "android_info": {
            "package_name": "com.example.insubria_survive",
            "certificate_hash": "a4ba95e5d9bef8d6f3c3b019987a7b32e68b25b0"
          }
        },
        {
          "client_id": "514391608735-kl6ro9c8c3ed5sia8kr42nnlkfv4nbia.apps.googleusercontent.com",
          "client_type": 3
        }
      ],
      "api_key": [
        {
          "current_key": "AIzaSyAMFBuzpbwZ4sa3-kA_F44BofCOCoMX9q4"
        }
      ],
      "services": {
        "appinvite_service": {
          "other_platform_oauth_client": [
            {
              "client_id": "514391608735-kl6ro9c8c3ed5sia8kr42nnlkfv4nbia.apps.googleusercontent.com",
              "client_type": 3
            }
          ]
        }
      }
    }
  ],
  "configuration_version": "1"
}